onegov.libres-0.3.0-py3.4-nspkg.pth
onegov/libres/__init__.py
onegov/libres/collection.py
onegov/libres/core.py
onegov/libres/models.py
onegov/libres/upgrade.py
onegov/libres/.gitignore
onegov/libres/tests/conftest.py
onegov/libres/tests/test_collection.py
onegov/libres/tests/test_resource.py
onegov/libres/tests/test_session.py
onegov.libres-0.3.0.dist-info/top_level.txt
onegov.libres-0.3.0.dist-info/namespace_packages.txt
onegov.libres-0.3.0.dist-info/entry_points.txt
onegov.libres-0.3.0.dist-info/METADATA
onegov.libres-0.3.0.dist-info/DESCRIPTION.rst
onegov.libres-0.3.0.dist-info/metadata.json
onegov.libres-0.3.0.dist-info/WHEEL
onegov.libres-0.3.0.dist-info/RECORD
